{"comic_burn_fatestaynight.md":"F9VP4SsI","comic_suspense_another.md":"YaEX8d7P","comic_suspense_thepromisedneverland.md":"1sr4wWJW","comic_relax_tamakomarket.md":"m4MmZrMZ","blog_wechatofficialaccount_wechatempower.md":"NY2EfwH_","blog_tool_introduction.md":"7kk4UCRv","comic_love_chunwu.md":"XYAFnqLd","comic_cure_youthpig.md":"bjUyKAbO","comic_reincarnation_re0.md":"v0FwQqdE","comic_reincarnation_unemployedreincarnation.md":"QWxq46VT","comic_cure_clannad.md":"8Y44iAI8","comic_burn_fatezero.md":"GF0DRMWe","comic_causedepression_homegirlfriend.md":"EFnQ2jt0","blog_jenkins_jenkins-and-gitlab.md":"ffbBOrNu","blog_tool_watt.md":"aabfWaTS","comic_causedepression_schooldays.md":"fxhIvHtG","blog_vitepress_base.md":"jVqGR0Nk","comic_burn_evilcrown.md":"g19lweJF","comic_cure_86.md":"NNSofpzZ","blog_electron_electron-vue.md":"zxCAo3wk","comic_burn_fullmetalalchemist.md":"LFENuIb_","comic_suspense_whentheycry.md":"HJYQz6fi","comic_suspense_summertimerendering.md":"u6R8_4ps","comic_relax_kon.md":"Hjz7jCpV","comic_relax_bocchitherock!.md":"UuX9WCs0","comic_love_middletwodiseases.md":"irTyOhvc","comic_burn_attackontitan.md":"rcBQ1sii","comic_suspense_danganronpa.md":"3sdGsnoZ","comic_burn_bungostraydogs.md":"yctWzDjJ","comic_suspense_heavenandmagicrealm.md":"zCF_BV2F","comic_writebefore_comicweb.md":"elhe_1MN","comic_suspense_steins.md":"5BaOXABD","index.md":"ALUgYPLv","comic_causedepression_whitealbum.md":"6xYUdisM","blog_vitepress_arrange.md":"bk4O-00s"}
